{
	"format_version": "1.8.0",
	"animations": {
		"animation.warg.attack_head": {
			"animation_length": 0.5,
			"bones": {
				"h_head": {
					"rotation": {
						"0.0": {
							"vector": [0, 0, 0]
						},
						"0.125": {
							"vector": [-32.08681, -3.21132, -14.65993]
						},
						"0.25": {
							"vector": [-2.08681, -3.21132, -14.65993]
						},
						"0.5": {
							"vector": [0, 0, 0]
						}
					},
					"scale": {
						"0.125": {
							"vector": [1, 1, 1]
						},
						"0.2083": {
							"vector": [1.4, 1.4, 1.4]
						},
						"0.25": {
							"vector": [1, 1, 1]
						}
					}
				},
				"jaw": {
					"rotation": {
						"0.0": {
							"vector": [0, 0, 0]
						},
						"0.125": {
							"vector": [50, 0, 0]
						},
						"0.25": {
							"vector": [-17.5, 0, 0]
						},
						"0.5": {
							"vector": [0, 0, 0]
						}
					}
				}
			}
		},
		"warg.animation.idle": {
			"loop": true,
			"animation_length": 2,
			"bones": {
				"warg": {
					"rotation": {
						"0.0": {
							"vector": [0, 0, 0]
						},
						"2.0": {
							"vector": [0, 0, 0]
						}
					},
					"position": {
						"0.0": {
							"vector": [0, 0, 0]
						},
						"2.0": {
							"vector": [0, 0, 0]
						}
					}
				},
				"body": {
					"rotation": {
						"0.0": {
							"vector": [0, 0, 0]
						},
						"2.0": {
							"vector": [0, 0, 0]
						}
					}
				},
				"front": {
					"rotation": {
						"0.0": {
							"vector": [0, 0, 0]
						},
						"2.0": {
							"vector": [0, 0, 0]
						}
					},
					"scale": {
						"0.0": {
							"vector": [1, 1, 1]
						},
						"1.0": {
							"vector": [1.03, 1.03, 1.03]
						},
						"2.0": {
							"vector": [1, 1, 1]
						}
					}
				},
				"back": {
					"rotation": {
						"0.0": {
							"vector": [0, 0, 0]
						},
						"2.0": {
							"vector": [0, 0, 0]
						}
					}
				},
				"legs": {
					"rotation": {
						"0.0": {
							"vector": [0, 0, 0]
						},
						"2.0": {
							"vector": [0, 0, 0]
						}
					}
				},
				"back2": {
					"rotation": {
						"0.0": {
							"vector": [0, 0, 0]
						},
						"2.0": {
							"vector": [0, 0, 0]
						}
					}
				},
				"L": {
					"rotation": {
						"0.0": {
							"vector": [0, 0, 0]
						},
						"2.0": {
							"vector": [0, 0, 0]
						}
					}
				},
				"kney2": {
					"rotation": {
						"0.0": {
							"vector": [0, 0, 0]
						},
						"2.0": {
							"vector": [0, 0, 0]
						}
					}
				},
				"foot2": {
					"rotation": {
						"0.0": {
							"vector": [0, 0, 0]
						},
						"2.0": {
							"vector": [0, 0, 0]
						}
					}
				},
				"R": {
					"rotation": {
						"0.0": {
							"vector": [0, 0, 0]
						},
						"2.0": {
							"vector": [0, 0, 0]
						}
					}
				},
				"kney": {
					"rotation": {
						"0.0": {
							"vector": [0, 0, 0]
						},
						"2.0": {
							"vector": [0, 0, 0]
						}
					}
				},
				"foot": {
					"rotation": {
						"0.0": {
							"vector": [0, 0, 0]
						},
						"2.0": {
							"vector": [0, 0, 0]
						}
					}
				},
				"front2": {
					"rotation": {
						"0.0": {
							"vector": [0, 0, 0]
						},
						"2.0": {
							"vector": [0, 0, 0]
						}
					}
				},
				"L2": {
					"rotation": {
						"0.0": {
							"vector": [0, 0, 0]
						},
						"2.0": {
							"vector": [0, 0, 0]
						}
					}
				},
				"forarm2": {
					"rotation": {
						"0.0": {
							"vector": [0, 0, 0]
						},
						"2.0": {
							"vector": [0, 0, 0]
						}
					}
				},
				"hand2": {
					"rotation": {
						"0.0": {
							"vector": [0, 0, 0]
						},
						"2.0": {
							"vector": [0, 0, 0]
						}
					}
				},
				"R2": {
					"rotation": {
						"0.0": {
							"vector": [0, 0, 0]
						},
						"2.0": {
							"vector": [0, 0, 0]
						}
					}
				},
				"forarm": {
					"rotation": {
						"0.0": {
							"vector": [0, 0, 0]
						},
						"2.0": {
							"vector": [0, 0, 0]
						}
					}
				},
				"hand": {
					"rotation": {
						"0.0": {
							"vector": [0, 0, 0]
						},
						"2.0": {
							"vector": [0, 0, 0]
						}
					}
				},
				"h_head": {
					"rotation": {
						"0.0": {
							"vector": [0, 0, 0]
						},
						"1.0": {
							"vector": [-2.5, 0, 0]
						},
						"1.0833": {
							"vector": [-3, 0, 0]
						},
						"2.0": {
							"vector": [0, 0, 0]
						}
					}
				},
				"jaw": {
					"rotation": {
						"0.0": {
							"vector": [0, 0, 0]
						},
						"1.0": {
							"vector": [7.5, 0, 0]
						},
						"1.0833": {
							"vector": [8, 0, 0]
						},
						"2.0": {
							"vector": [0, 0, 0]
						}
					}
				},
				"tail": {
					"rotation": {
						"0.0": {
							"vector": [0, 0, 0]
						},
						"1.0": {
							"vector": [5, 0, 0]
						},
						"1.0833": {
							"vector": [6, 0, 0]
						},
						"2.0": {
							"vector": [0, 0, 0]
						}
					}
				},
				"section2": {
					"rotation": {
						"0.0": {
							"vector": [0, 0, 0]
						},
						"1.0": {
							"vector": [7.5, 0, 0]
						},
						"1.0833": {
							"vector": [8, 0, 0]
						},
						"2.0": {
							"vector": [0, 0, 0]
						}
					}
				}
			}
		},
		"animation.warg.run": {
			"loop": true,
			"animation_length": 0.375,
			"bones": {
				"warg": {
					"rotation": {
						"0.0": {
							"vector": [-5, -2.5, 0]
						},
						"0.0833": {
							"vector": [7.5, -2.5, 0]
						},
						"0.2083": {
							"vector": [0, -2.5, 0]
						},
						"0.375": {
							"vector": [-5, -2.5, 0]
						}
					},
					"position": {
						"0.0": {
							"vector": [0, 3, 0]
						},
						"0.0833": {
							"vector": [0, 0, 0]
						},
						"0.2083": {
							"vector": [0, -2, 0]
						},
						"0.375": {
							"vector": [0, 3, 0]
						}
					}
				},
				"L": {
					"rotation": {
						"0.0": {
							"vector": [17.5, 0, 0]
						},
						"0.0833": {
							"vector": [-65, 0, 0]
						},
						"0.2083": {
							"vector": [-20, 0, 0]
						},
						"0.375": {
							"vector": [17.5, 0, 0]
						}
					},
					"position": {
						"0.0": {
							"vector": [0, 0, 0]
						},
						"0.0417": {
							"vector": [0, 2, 0]
						},
						"0.1667": {
							"vector": [0, 0, 0]
						},
						"0.375": {
							"vector": [0, 0, 0]
						}
					}
				},
				"kney2": {
					"rotation": {
						"0.0": {
							"vector": [37.5, 0, 0]
						},
						"0.2083": {
							"vector": [45, 0, 0]
						},
						"0.375": {
							"vector": [37.5, 0, 0]
						}
					}
				},
				"foot2": {
					"rotation": {
						"0.0": {
							"vector": [80, 0, 0]
						},
						"0.0833": {
							"vector": [0, 0, 0]
						},
						"0.2083": {
							"vector": [-25, 0, 0]
						},
						"0.375": {
							"vector": [80, 0, 0]
						}
					}
				},
				"R": {
					"rotation": {
						"0.0": {
							"vector": [20, 0, 0]
						},
						"0.0833": {
							"vector": [-65, 0, 0]
						},
						"0.2083": {
							"vector": [-20, 0, 0]
						},
						"0.375": {
							"vector": [20, 0, 0]
						}
					},
					"position": {
						"0.0": {
							"vector": [0, 0, 0]
						},
						"0.0417": {
							"vector": [0, 2, 0]
						},
						"0.1667": {
							"vector": [0, 0, 0]
						},
						"0.375": {
							"vector": [0, 0, 0]
						}
					}
				},
				"kney": {
					"rotation": {
						"0.0": {
							"vector": [22.3677, -0.62197, 0.50433]
						},
						"0.2083": {
							"vector": [45, 0, 0]
						},
						"0.375": {
							"vector": [22.3677, -0.62197, 0.50433]
						}
					}
				},
				"foot": {
					"rotation": {
						"0.0": {
							"vector": [72.33763, -1.88966, -0.92505]
						},
						"0.0833": {
							"vector": [0, 0, 0]
						},
						"0.2083": {
							"vector": [-25, 0, 0]
						},
						"0.375": {
							"vector": [72.33763, -1.88966, -0.92505]
						}
					}
				},
				"L2": {
					"rotation": {
						"0.0": {
							"vector": [-35, 0, 0]
						},
						"0.0833": {
							"vector": [-23.5, 0, 0]
						},
						"0.2083": {
							"vector": [50, 0, 0]
						},
						"0.2917": {
							"vector": [17.5, 0, 0]
						},
						"0.375": {
							"vector": [-35, 0, 0]
						}
					},
					"position": {
						"0.0": {
							"vector": [0, 0, 0]
						},
						"0.0833": {
							"vector": [0, -0.33, 0]
						},
						"0.125": {
							"vector": [0, 2.11, 0]
						},
						"0.2083": {
							"vector": [0, 1, 0]
						},
						"0.2917": {
							"vector": [0, 3, 0]
						},
						"0.375": {
							"vector": [0, 0, 0]
						}
					}
				},
				"forarm2": {
					"rotation": {
						"0.0": {
							"vector": [-12.5, 0, 0]
						},
						"0.0833": {
							"vector": [15, 0, 0]
						},
						"0.2083": {
							"vector": [-2.5, 0, 0]
						},
						"0.2917": {
							"vector": [-92.5, 0, 0]
						},
						"0.375": {
							"vector": [-12.5, 0, 0]
						}
					}
				},
				"hand2": {
					"rotation": {
						"0.0": {
							"vector": [15, 0, 0]
						},
						"0.0833": {
							"vector": [2.5, 0, 0]
						},
						"0.2083": {
							"vector": [-47.5, 0, 0]
						},
						"0.2917": {
							"vector": [92.5, 0, 0]
						},
						"0.375": {
							"vector": [15, 0, 0]
						}
					}
				},
				"R2": {
					"rotation": {
						"0.0": {
							"vector": [0, 0, 0]
						},
						"0.0833": {
							"vector": [-23.5, 0, 0]
						},
						"0.2083": {
							"vector": [50, 0, 0]
						},
						"0.2917": {
							"vector": [17.5, 0, 0]
						},
						"0.375": {
							"vector": [0, 0, 0]
						}
					},
					"position": {
						"0.0": {
							"vector": [0, 0, 0]
						},
						"0.0833": {
							"vector": [0, -0.33, 0]
						},
						"0.125": {
							"vector": [0, 2.11, 0]
						},
						"0.2083": {
							"vector": [0, 1, 0]
						},
						"0.2917": {
							"vector": [0, 3, 0]
						},
						"0.375": {
							"vector": [0, 0, 0]
						}
					}
				},
				"forarm": {
					"rotation": {
						"0.0": {
							"vector": [-45, 0, 0]
						},
						"0.0833": {
							"vector": [15, 0, 0]
						},
						"0.2083": {
							"vector": [-2.5, 0, 0]
						},
						"0.2917": {
							"vector": [-92.5, 0, 0]
						},
						"0.375": {
							"vector": [-45, 0, 0]
						}
					}
				},
				"hand": {
					"rotation": {
						"0.0": {
							"vector": [0, 0, 0]
						},
						"0.0833": {
							"vector": [0, 0, 0]
						},
						"0.2083": {
							"vector": [-47.5, 0, 0]
						},
						"0.2917": {
							"vector": [95, 0, 0]
						},
						"0.375": {
							"vector": [0, 0, 0]
						}
					}
				}
			}
		},
		"warg.animation.walk": {
			"loop": true,
			"animation_length": 1.25,
			"bones": {
				"warg": {
					"rotation": {
						"0.0": {
							"vector": [0, -2.5, 0]
						},
						"0.625": {
							"vector": [0, 2.5, 0]
						},
						"1.25": {
							"vector": [0, -2.5, 0]
						}
					},
					"position": {
						"0.0": {
							"vector": [0, -1, 0]
						},
						"0.125": {
							"vector": [0, -1, 0]
						},
						"0.4583": {
							"vector": [0, 0.67, 0]
						},
						"0.625": {
							"vector": [0, -1, 0]
						},
						"0.7917": {
							"vector": [0, -1, 0]
						},
						"1.125": {
							"vector": [0, 0.67, 0]
						},
						"1.25": {
							"vector": [0, -1, 0]
						}
					}
				},
				"L": {
					"rotation": {
						"0.0": {
							"vector": [17.5, 0, 0]
						},
						"0.3333": {
							"vector": [-30.67, 0, 0]
						},
						"0.5": {
							"vector": [-53.5, 0, 0]
						},
						"0.625": {
							"vector": [-40, 0, 0]
						},
						"1.25": {
							"vector": [17.5, 0, 0]
						}
					}
				},
				"kney2": {
					"rotation": {
						"0.0": {
							"vector": [-17.5, 0, 0]
						},
						"0.1667": {
							"vector": [13.29805, -0.16586, 0.13449]
						},
						"0.3333": {
							"vector": [45.23247, -0.33172, 0.26898]
						},
						"0.5": {
							"vector": [28.03662, -0.77656, 2.25287]
						},
						"0.625": {
							"vector": [32.3677, -0.62197, 0.50433]
						},
						"0.8333": {
							"vector": [25.74513, -0.41464, 0.33622]
						},
						"1.0833": {
							"vector": [-22.70195, -0.16586, 0.13449]
						},
						"1.25": {
							"vector": [-17.5, 0, 0]
						}
					}
				},
				"foot2": {
					"rotation": {
						"0.0": {
							"vector": [0, 0, 0]
						},
						"0.1667": {
							"vector": [-15.5, 0, 0]
						},
						"0.3333": {
							"vector": [10.36, 0, 0]
						},
						"0.4167": {
							"vector": [29.54, 0, 0]
						},
						"0.625": {
							"vector": [7.5, 0, 0]
						},
						"0.8333": {
							"vector": [-5, 0, 0]
						},
						"1.0833": {
							"vector": [20.5, 0, 0]
						},
						"1.25": {
							"vector": [0, 0, 0]
						}
					}
				},
				"R": {
					"rotation": {
						"0.0": {
							"vector": [-40, 0, 0]
						},
						"0.625": {
							"vector": [17.5, 0, 0]
						},
						"0.9583": {
							"vector": [-30.67, 0, 0]
						},
						"1.125": {
							"vector": [-53.5, 0, 0]
						},
						"1.25": {
							"vector": [-40, 0, 0]
						}
					}
				},
				"kney": {
					"rotation": {
						"0.0": {
							"vector": [32.3677, -0.62197, 0.50433]
						},
						"0.2083": {
							"vector": [25.74513, -0.41464, 0.33622]
						},
						"0.4583": {
							"vector": [-22.70195, -0.16586, 0.13449]
						},
						"0.625": {
							"vector": [-17.5, 0, 0]
						},
						"0.7917": {
							"vector": [13.29805, -0.16586, 0.13449]
						},
						"0.9583": {
							"vector": [45.23247, -0.33172, 0.26898]
						},
						"1.125": {
							"vector": [28.03662, -0.77656, 2.25287]
						},
						"1.25": {
							"vector": [32.3677, -0.62197, 0.50433]
						}
					}
				},
				"foot": {
					"rotation": {
						"0.0": {
							"vector": [7.5, 0, 0]
						},
						"0.2083": {
							"vector": [-5, 0, 0]
						},
						"0.4583": {
							"vector": [20.5, 0, 0]
						},
						"0.625": {
							"vector": [0, 0, 0]
						},
						"0.7917": {
							"vector": [-15.5, 0, 0]
						},
						"0.9583": {
							"vector": [10.36, 0, 0]
						},
						"1.0417": {
							"vector": [29.54, 0, 0]
						},
						"1.25": {
							"vector": [7.5, 0, 0]
						}
					}
				},
				"L2": {
					"rotation": {
						"0.0": {
							"vector": [-17.5, 0, 0]
						},
						"0.625": {
							"vector": [42.5, 0, 0]
						},
						"0.75": {
							"vector": [48, 0, 0]
						},
						"0.875": {
							"vector": [66.63, 0, 0]
						},
						"1.0833": {
							"vector": [-10.11, 0, 0]
						},
						"1.25": {
							"vector": [-17.5, 0, 0]
						}
					}
				},
				"forarm2": {
					"rotation": {
						"0.0": {
							"vector": [15, 0, 0]
						},
						"0.1667": {
							"vector": [-6.33, 0, 0]
						},
						"0.375": {
							"vector": [-6.41, 0, 0]
						},
						"0.625": {
							"vector": [10, 0, 0]
						},
						"0.75": {
							"vector": [-4, 0, 0]
						},
						"0.875": {
							"vector": [-59.25, 0, 0]
						},
						"1.0833": {
							"vector": [-60.5, 0, 0]
						},
						"1.25": {
							"vector": [15, 0, 0]
						}
					}
				},
				"hand2": {
					"rotation": {
						"0.0": {
							"vector": [2.5, 0, 0]
						},
						"0.1667": {
							"vector": [7.83, 0, 0]
						},
						"0.375": {
							"vector": [-12.09, 0, 0]
						},
						"0.625": {
							"vector": [-52.5, 0, 0]
						},
						"0.75": {
							"vector": [-44, 0, 0]
						},
						"0.875": {
							"vector": [24.5, 0, 0]
						},
						"1.0833": {
							"vector": [114.78, 0, 0]
						},
						"1.25": {
							"vector": [2.5, 0, 0]
						}
					}
				},
				"R2": {
					"rotation": {
						"0.0": {
							"vector": [42.5, 0, 0]
						},
						"0.125": {
							"vector": [48, 0, 0]
						},
						"0.25": {
							"vector": [66.63, 0, 0]
						},
						"0.4583": {
							"vector": [-10.11, 0, 0]
						},
						"0.625": {
							"vector": [-17.5, 0, 0]
						},
						"1.25": {
							"vector": [42.5, 0, 0]
						}
					}
				},
				"forarm": {
					"rotation": {
						"0.0": {
							"vector": [10, 0, 0]
						},
						"0.125": {
							"vector": [-4, 0, 0]
						},
						"0.25": {
							"vector": [-59.25, 0, 0]
						},
						"0.4583": {
							"vector": [-60.5, 0, 0]
						},
						"0.625": {
							"vector": [15, 0, 0]
						},
						"0.7917": {
							"vector": [-6.33, 0, 0]
						},
						"1.0": {
							"vector": [-6.41, 0, 0]
						},
						"1.25": {
							"vector": [10, 0, 0]
						}
					}
				},
				"hand": {
					"rotation": {
						"0.0": {
							"vector": [-52.5, 0, 0]
						},
						"0.125": {
							"vector": [-44, 0, 0]
						},
						"0.25": {
							"vector": [24.5, 0, 0]
						},
						"0.4583": {
							"vector": [114.78, 0, 0]
						},
						"0.625": {
							"vector": [2.5, 0, 0]
						},
						"0.7917": {
							"vector": [7.83, 0, 0]
						},
						"1.0": {
							"vector": [-12.09, 0, 0]
						},
						"1.25": {
							"vector": [-52.5, 0, 0]
						}
					}
				}
			}
		},
		"warg.animation.walk_head": {
			"loop": true,
			"animation_length": 1.25,
			"bones": {
				"h_head": {
					"rotation": {
						"0.0": {
							"vector": [0.10395, 2.27982, 2.49245]
						},
						"0.125": {
							"vector": [2.60395, 1.36789, 1.49547]
						},
						"0.4167": {
							"vector": [-3.85438, -0.75994, -0.83082]
						},
						"0.625": {
							"vector": [0.10395, -2.27982, -2.49245]
						},
						"0.75": {
							"vector": [2.45711, 2.02357, -3.46355]
						},
						"1.0417": {
							"vector": [-3.82233, -0.70925, -3.33051]
						},
						"1.25": {
							"vector": [0.10395, 2.27982, 2.49245]
						}
					}
				},
				"jaw": {
					"rotation": {
						"0.0": {
							"vector": [0, 0, 0]
						},
						"0.125": {
							"vector": [5, 0, 0]
						},
						"0.4167": {
							"vector": [0, 0, 0]
						},
						"0.625": {
							"vector": [0, 0, 0]
						},
						"0.75": {
							"vector": [5, 0, 0]
						},
						"1.0417": {
							"vector": [0, 0, 0]
						},
						"1.25": {
							"vector": [0, 0, 0]
						}
					}
				}
			}
		},
		"warg.animation.run_head": {
			"loop": true,
			"animation_length": 0.375,
			"bones": {
				"h_head": {
					"rotation": {
						"0.0": {
							"vector": [0.10395, 2.27982, 2.49245]
						},
						"0.0833": {
							"vector": [-2.39605, 2.27982, 2.49245]
						},
						"0.2083": {
							"vector": [-14.89605, 2.27982, 2.49245]
						},
						"0.375": {
							"vector": [0.10395, 2.27982, 2.49245]
						}
					}
				},
				"jaw": {
					"rotation": {
						"0.0": {
							"vector": [-2.5, 0, 0]
						},
						"0.0833": {
							"vector": [-12.5, 0, 0]
						},
						"0.1667": {
							"vector": [7.03, 0, 0]
						},
						"0.375": {
							"vector": [-2.5, 0, 0]
						}
					}
				}
			}
		}
	},
	"geckolib_format_version": 2
}